{
  "count": 15,
  "next": null,
  "previous": null,
  "results": [
    {
      "id": 23,
      "type": "credential",
      "url": "/api/v2/credentials/23/",
      "related": {
        "created_by": "/api/v2/users/1/",
        "modified_by": "/api/v2/users/1/",
        "activity_stream": "/api/v2/credentials/23/activity_stream/",
        "access_list": "/api/v2/credentials/23/access_list/",
        "object_roles": "/api/v2/credentials/23/object_roles/",
        "owner_users": "/api/v2/credentials/23/owner_users/",
        "owner_teams": "/api/v2/credentials/23/owner_teams/",
        "copy": "/api/v2/credentials/23/copy/",
        "input_sources": "/api/v2/credentials/23/input_sources/",
        "credential_type": "/api/v2/credential_types/1/"
      },
      "summary_fields": {
        "credential_type": {
          "id": 1,
          "name": "Machine",
          "description": ""
        },
        "created_by": {
          "id": 1,
          "username": "admin",
          "first_name": "",
          "last_name": ""
        },
        "modified_by": {
          "id": 1,
          "username": "admin",
          "first_name": "",
          "last_name": ""
        },
        "object_roles": {
          "admin_role": {
            "description": "Can manage all aspects of the credential",
            "name": "Admin",
            "id": 499
          },
          "use_role": {
            "description": "Can use the credential in a job template",
            "name": "Use",
            "id": 500
          },
          "read_role": {
            "description": "May view settings for the credential",
            "name": "Read",
            "id": 501
          }
        },
        "user_capabilities": {
          "edit": true,
          "delete": true,
          "copy": true,
          "use": true
        },
        "owners": []
      },
      "created": "2023-02-10T18:12:51.492266Z",
      "modified": "2023-02-10T18:12:51.492280Z",
      "name": "alex",
      "description": "",
      "organization": null,
      "credential_type": 1,
      "managed": false,
      "inputs": {},
      "kind": "ssh",
      "cloud": false,
      "kubernetes": false
    },
    {
      "id": 2,
      "type": "credential",
      "url": "/api/v2/credentials/2/",
      "related": {
        "created_by": "/api/v2/users/1/",
        "modified_by": "/api/v2/users/1/",
        "activity_stream": "/api/v2/credentials/2/activity_stream/",
        "access_list": "/api/v2/credentials/2/access_list/",
        "object_roles": "/api/v2/credentials/2/object_roles/",
        "owner_users": "/api/v2/credentials/2/owner_users/",
        "owner_teams": "/api/v2/credentials/2/owner_teams/",
        "copy": "/api/v2/credentials/2/copy/",
        "input_sources": "/api/v2/credentials/2/input_sources/",
        "credential_type": "/api/v2/credential_types/18/"
      },
      "summary_fields": {
        "credential_type": {
          "id": 18,
          "name": "Ansible Galaxy/Automation Hub API Token",
          "description": ""
        },
        "created_by": {
          "id": 1,
          "username": "admin",
          "first_name": "",
          "last_name": ""
        },
        "modified_by": {
          "id": 1,
          "username": "admin",
          "first_name": "",
          "last_name": ""
        },
        "object_roles": {
          "admin_role": {
            "description": "Can manage all aspects of the credential",
            "name": "Admin",
            "id": 23
          },
          "use_role": {
            "description": "Can use the credential in a job template",
            "name": "Use",
            "id": 24
          },
          "read_role": {
            "description": "May view settings for the credential",
            "name": "Read",
            "id": 25
          }
        },
        "user_capabilities": {
          "edit": false,
          "delete": false,
          "copy": true,
          "use": true
        },
        "owners": []
      },
      "created": "2022-12-09T15:26:49.544132Z",
      "modified": "2022-12-09T15:26:49.544146Z",
      "name": "Ansible Galaxy",
      "description": "",
      "organization": null,
      "credential_type": 18,
      "managed": true,
      "inputs": {
        "url": "https://galaxy.ansible.com/"
      },
      "kind": "galaxy_api_token",
      "cloud": false,
      "kubernetes": false
    },
    {
      "id": 12,
      "type": "credential",
      "url": "/api/v2/credentials/12/",
      "related": {
        "created_by": "/api/v2/users/1/",
        "modified_by": "/api/v2/users/1/",
        "activity_stream": "/api/v2/credentials/12/activity_stream/",
        "access_list": "/api/v2/credentials/12/access_list/",
        "object_roles": "/api/v2/credentials/12/object_roles/",
        "owner_users": "/api/v2/credentials/12/owner_users/",
        "owner_teams": "/api/v2/credentials/12/owner_teams/",
        "copy": "/api/v2/credentials/12/copy/",
        "input_sources": "/api/v2/credentials/12/input_sources/",
        "credential_type": "/api/v2/credential_types/5/",
        "user": "/api/v2/users/1/"
      },
      "summary_fields": {
        "credential_type": {
          "id": 5,
          "name": "Amazon Web Services",
          "description": ""
        },
        "created_by": {
          "id": 1,
          "username": "admin",
          "first_name": "",
          "last_name": ""
        },
        "modified_by": {
          "id": 1,
          "username": "admin",
          "first_name": "",
          "last_name": ""
        },
        "object_roles": {
          "admin_role": {
            "description": "Can manage all aspects of the credential",
            "name": "Admin",
            "id": 445
          },
          "use_role": {
            "description": "Can use the credential in a job template",
            "name": "Use",
            "id": 446
          },
          "read_role": {
            "description": "May view settings for the credential",
            "name": "Read",
            "id": 447
          }
        },
        "user_capabilities": {
          "edit": true,
          "delete": true,
          "copy": true,
          "use": true
        },
        "owners": [
          {
            "id": 1,
            "type": "user",
            "name": "admin",
            "description": " ",
            "url": "/api/v2/users/1/"
          }
        ]
      },
      "created": "2023-02-01T20:36:45.890927Z",
      "modified": "2023-02-01T20:36:45.890941Z",
      "name": "awx",
      "description": "",
      "organization": null,
      "credential_type": 5,
      "managed": false,
      "inputs": {
        "password": "$encrypted$",
        "username": "sadfgh"
      },
      "kind": "aws",
      "cloud": true,
      "kubernetes": false
    },
    {
      "id": 1,
      "type": "credential",
      "url": "/api/v2/credentials/1/",
      "related": {
        "created_by": "/api/v2/users/1/",
        "modified_by": "/api/v2/users/1/",
        "activity_stream": "/api/v2/credentials/1/activity_stream/",
        "access_list": "/api/v2/credentials/1/access_list/",
        "object_roles": "/api/v2/credentials/1/object_roles/",
        "owner_users": "/api/v2/credentials/1/owner_users/",
        "owner_teams": "/api/v2/credentials/1/owner_teams/",
        "copy": "/api/v2/credentials/1/copy/",
        "input_sources": "/api/v2/credentials/1/input_sources/",
        "credential_type": "/api/v2/credential_types/1/",
        "user": "/api/v2/users/1/"
      },
      "summary_fields": {
        "credential_type": {
          "id": 1,
          "name": "Machine",
          "description": ""
        },
        "created_by": {
          "id": 1,
          "username": "admin",
          "first_name": "",
          "last_name": ""
        },
        "modified_by": {
          "id": 1,
          "username": "admin",
          "first_name": "",
          "last_name": ""
        },
        "object_roles": {
          "admin_role": {
            "description": "Can manage all aspects of the credential",
            "name": "Admin",
            "id": 20
          },
          "use_role": {
            "description": "Can use the credential in a job template",
            "name": "Use",
            "id": 21
          },
          "read_role": {
            "description": "May view settings for the credential",
            "name": "Read",
            "id": 22
          }
        },
        "user_capabilities": {
          "edit": true,
          "delete": true,
          "copy": true,
          "use": true
        },
        "owners": [
          {
            "id": 1,
            "type": "user",
            "name": "admin",
            "description": " ",
            "url": "/api/v2/users/1/"
          }
        ]
      },
      "created": "2022-12-09T15:26:49.466499Z",
      "modified": "2022-12-09T15:26:49.466513Z",
      "name": "Demo Credential",
      "description": "",
      "organization": null,
      "credential_type": 1,
      "managed": false,
      "inputs": {
        "username": "admin"
      },
      "kind": "ssh",
      "cloud": false,
      "kubernetes": false
    },
    {
      "id": 13,
      "type": "credential",
      "url": "/api/v2/credentials/13/",
      "related": {
        "created_by": "/api/v2/users/1/",
        "modified_by": "/api/v2/users/1/",
        "activity_stream": "/api/v2/credentials/13/activity_stream/",
        "access_list": "/api/v2/credentials/13/access_list/",
        "object_roles": "/api/v2/credentials/13/object_roles/",
        "owner_users": "/api/v2/credentials/13/owner_users/",
        "owner_teams": "/api/v2/credentials/13/owner_teams/",
        "copy": "/api/v2/credentials/13/copy/",
        "input_sources": "/api/v2/credentials/13/input_sources/",
        "credential_type": "/api/v2/credential_types/9/",
        "user": "/api/v2/users/1/"
      },
      "summary_fields": {
        "credential_type": {
          "id": 9,
          "name": "Google Compute Engine",
          "description": ""
        },
        "created_by": {
          "id": 1,
          "username": "admin",
          "first_name": "",
          "last_name": ""
        },
        "modified_by": {
          "id": 1,
          "username": "admin",
          "first_name": "",
          "last_name": ""
        },
        "object_roles": {
          "admin_role": {
            "description": "Can manage all aspects of the credential",
            "name": "Admin",
            "id": 448
          },
          "use_role": {
            "description": "Can use the credential in a job template",
            "name": "Use",
            "id": 449
          },
          "read_role": {
            "description": "May view settings for the credential",
            "name": "Read",
            "id": 450
          }
        },
        "user_capabilities": {
          "edit": true,
          "delete": true,
          "copy": true,
          "use": true
        },
        "owners": [
          {
            "id": 1,
            "type": "user",
            "name": "admin",
            "description": " ",
            "url": "/api/v2/users/1/"
          }
        ]
      },
      "created": "2023-02-01T20:39:44.927245Z",
      "modified": "2023-02-01T20:39:44.927259Z",
      "name": "GCE",
      "description": "",
      "organization": null,
      "credential_type": 9,
      "managed": false,
      "inputs": {
        "project": "",
        "username": "a@g.com",
        "ssh_key_data": "$encrypted$"
      },
      "kind": "gce",
      "cloud": true,
      "kubernetes": false
    },
    {
      "id": 22,
      "type": "credential",
      "url": "/api/v2/credentials/22/",
      "related": {
        "created_by": "/api/v2/users/1/",
        "modified_by": "/api/v2/users/1/",
        "activity_stream": "/api/v2/credentials/22/activity_stream/",
        "access_list": "/api/v2/credentials/22/access_list/",
        "object_roles": "/api/v2/credentials/22/object_roles/",
        "owner_users": "/api/v2/credentials/22/owner_users/",
        "owner_teams": "/api/v2/credentials/22/owner_teams/",
        "copy": "/api/v2/credentials/22/copy/",
        "input_sources": "/api/v2/credentials/22/input_sources/",
        "credential_type": "/api/v2/credential_types/11/",
        "user": "/api/v2/users/1/"
      },
      "summary_fields": {
        "credential_type": {
          "id": 11,
          "name": "GitHub Personal Access Token",
          "description": ""
        },
        "created_by": {
          "id": 1,
          "username": "admin",
          "first_name": "",
          "last_name": ""
        },
        "modified_by": {
          "id": 1,
          "username": "admin",
          "first_name": "",
          "last_name": ""
        },
        "object_roles": {
          "admin_role": {
            "description": "Can manage all aspects of the credential",
            "name": "Admin",
            "id": 475
          },
          "use_role": {
            "description": "Can use the credential in a job template",
            "name": "Use",
            "id": 476
          },
          "read_role": {
            "description": "May view settings for the credential",
            "name": "Read",
            "id": 477
          }
        },
        "user_capabilities": {
          "edit": true,
          "delete": true,
          "copy": true,
          "use": true
        },
        "owners": [
          {
            "id": 1,
            "type": "user",
            "name": "admin",
            "description": " ",
            "url": "/api/v2/users/1/"
          }
        ]
      },
      "created": "2023-02-08T20:03:00.833586Z",
      "modified": "2023-02-08T20:03:00.833600Z",
      "name": "github",
      "description": "",
      "organization": null,
      "credential_type": 11,
      "managed": false,
      "inputs": {
        "token": "$encrypted$"
      },
      "kind": "github_token",
      "cloud": false,
      "kubernetes": false
    },
    {
      "id": 20,
      "type": "credential",
      "url": "/api/v2/credentials/20/",
      "related": {
        "created_by": "/api/v2/users/1/",
        "modified_by": "/api/v2/users/1/",
        "activity_stream": "/api/v2/credentials/20/activity_stream/",
        "access_list": "/api/v2/credentials/20/access_list/",
        "object_roles": "/api/v2/credentials/20/object_roles/",
        "owner_users": "/api/v2/credentials/20/owner_users/",
        "owner_teams": "/api/v2/credentials/20/owner_teams/",
        "copy": "/api/v2/credentials/20/copy/",
        "input_sources": "/api/v2/credentials/20/input_sources/",
        "credential_type": "/api/v2/credential_types/19/",
        "user": "/api/v2/users/1/"
      },
      "summary_fields": {
        "credential_type": {
          "id": 19,
          "name": "GPG Public Key",
          "description": ""
        },
        "created_by": {
          "id": 1,
          "username": "admin",
          "first_name": "",
          "last_name": ""
        },
        "modified_by": {
          "id": 1,
          "username": "admin",
          "first_name": "",
          "last_name": ""
        },
        "object_roles": {
          "admin_role": {
            "description": "Can manage all aspects of the credential",
            "name": "Admin",
            "id": 469
          },
          "use_role": {
            "description": "Can use the credential in a job template",
            "name": "Use",
            "id": 470
          },
          "read_role": {
            "description": "May view settings for the credential",
            "name": "Read",
            "id": 471
          }
        },
        "user_capabilities": {
          "edit": true,
          "delete": true,
          "copy": true,
          "use": true
        },
        "owners": [
          {
            "id": 1,
            "type": "user",
            "name": "admin",
            "description": " ",
            "url": "/api/v2/users/1/"
          }
        ]
      },
      "created": "2023-02-01T20:42:34.487861Z",
      "modified": "2023-02-01T20:42:34.487875Z",
      "name": "gpg",
      "description": "",
      "organization": null,
      "credential_type": 19,
      "managed": false,
      "inputs": {
        "gpg_public_key": "$encrypted$"
      },
      "kind": "gpg_public_key",
      "cloud": false,
      "kubernetes": false
    },
    {
      "id": 14,
      "type": "credential",
      "url": "/api/v2/credentials/14/",
      "related": {
        "created_by": "/api/v2/users/1/",
        "modified_by": "/api/v2/users/1/",
        "activity_stream": "/api/v2/credentials/14/activity_stream/",
        "access_list": "/api/v2/credentials/14/access_list/",
        "object_roles": "/api/v2/credentials/14/object_roles/",
        "owner_users": "/api/v2/credentials/14/owner_users/",
        "owner_teams": "/api/v2/credentials/14/owner_teams/",
        "copy": "/api/v2/credentials/14/copy/",
        "input_sources": "/api/v2/credentials/14/input_sources/",
        "credential_type": "/api/v2/credential_types/10/",
        "user": "/api/v2/users/1/"
      },
      "summary_fields": {
        "credential_type": {
          "id": 10,
          "name": "Microsoft Azure Resource Manager",
          "description": ""
        },
        "created_by": {
          "id": 1,
          "username": "admin",
          "first_name": "",
          "last_name": ""
        },
        "modified_by": {
          "id": 1,
          "username": "admin",
          "first_name": "",
          "last_name": ""
        },
        "object_roles": {
          "admin_role": {
            "description": "Can manage all aspects of the credential",
            "name": "Admin",
            "id": 451
          },
          "use_role": {
            "description": "Can use the credential in a job template",
            "name": "Use",
            "id": 452
          },
          "read_role": {
            "description": "May view settings for the credential",
            "name": "Read",
            "id": 453
          }
        },
        "user_capabilities": {
          "edit": true,
          "delete": true,
          "copy": true,
          "use": true
        },
        "owners": [
          {
            "id": 1,
            "type": "user",
            "name": "admin",
            "description": " ",
            "url": "/api/v2/users/1/"
          }
        ]
      },
      "created": "2023-02-01T20:40:17.937020Z",
      "modified": "2023-02-01T20:40:17.937034Z",
      "name": "microsoft azure",
      "description": "",
      "organization": null,
      "credential_type": 10,
      "managed": false,
      "inputs": {
        "client": "",
        "tenant": "",
        "username": "",
        "subscription": "dfgh",
        "cloud_environment": ""
      },
      "kind": "azure_rm",
      "cloud": true,
      "kubernetes": false
    },
    {
      "id": 21,
      "type": "credential",
      "url": "/api/v2/credentials/21/",
      "related": {
        "created_by": "/api/v2/users/1/",
        "modified_by": "/api/v2/users/1/",
        "activity_stream": "/api/v2/credentials/21/activity_stream/",
        "access_list": "/api/v2/credentials/21/access_list/",
        "object_roles": "/api/v2/credentials/21/object_roles/",
        "owner_users": "/api/v2/credentials/21/owner_users/",
        "owner_teams": "/api/v2/credentials/21/owner_teams/",
        "copy": "/api/v2/credentials/21/copy/",
        "input_sources": "/api/v2/credentials/21/input_sources/",
        "credential_type": "/api/v2/credential_types/16/",
        "user": "/api/v2/users/1/"
      },
      "summary_fields": {
        "credential_type": {
          "id": 16,
          "name": "OpenShift or Kubernetes API Bearer Token",
          "description": ""
        },
        "created_by": {
          "id": 1,
          "username": "admin",
          "first_name": "",
          "last_name": ""
        },
        "modified_by": {
          "id": 1,
          "username": "admin",
          "first_name": "",
          "last_name": ""
        },
        "object_roles": {
          "admin_role": {
            "description": "Can manage all aspects of the credential",
            "name": "Admin",
            "id": 472
          },
          "use_role": {
            "description": "Can use the credential in a job template",
            "name": "Use",
            "id": 473
          },
          "read_role": {
            "description": "May view settings for the credential",
            "name": "Read",
            "id": 474
          }
        },
        "user_capabilities": {
          "edit": true,
          "delete": true,
          "copy": true,
          "use": true
        },
        "owners": [
          {
            "id": 1,
            "type": "user",
            "name": "admin",
            "description": " ",
            "url": "/api/v2/users/1/"
          }
        ]
      },
      "created": "2023-02-01T20:43:00.829371Z",
      "modified": "2023-02-01T20:43:00.829385Z",
      "name": "oopen",
      "description": "",
      "organization": null,
      "credential_type": 16,
      "managed": false,
      "inputs": {
        "host": "https://www.google.com",
        "verify_ssl": true,
        "bearer_token": "$encrypted$"
      },
      "kind": "kubernetes_bearer_token",
      "cloud": false,
      "kubernetes": true
    },
    {
      "id": 15,
      "type": "credential",
      "url": "/api/v2/credentials/15/",
      "related": {
        "created_by": "/api/v2/users/1/",
        "modified_by": "/api/v2/users/1/",
        "activity_stream": "/api/v2/credentials/15/activity_stream/",
        "access_list": "/api/v2/credentials/15/access_list/",
        "object_roles": "/api/v2/credentials/15/object_roles/",
        "owner_users": "/api/v2/credentials/15/owner_users/",
        "owner_teams": "/api/v2/credentials/15/owner_teams/",
        "copy": "/api/v2/credentials/15/copy/",
        "input_sources": "/api/v2/credentials/15/input_sources/",
        "credential_type": "/api/v2/credential_types/6/",
        "user": "/api/v2/users/1/"
      },
      "summary_fields": {
        "credential_type": {
          "id": 6,
          "name": "OpenStack",
          "description": ""
        },
        "created_by": {
          "id": 1,
          "username": "admin",
          "first_name": "",
          "last_name": ""
        },
        "modified_by": {
          "id": 1,
          "username": "admin",
          "first_name": "",
          "last_name": ""
        },
        "object_roles": {
          "admin_role": {
            "description": "Can manage all aspects of the credential",
            "name": "Admin",
            "id": 454
          },
          "use_role": {
            "description": "Can use the credential in a job template",
            "name": "Use",
            "id": 455
          },
          "read_role": {
            "description": "May view settings for the credential",
            "name": "Read",
            "id": 456
          }
        },
        "user_capabilities": {
          "edit": true,
          "delete": true,
          "copy": true,
          "use": true
        },
        "owners": [
          {
            "id": 1,
            "type": "user",
            "name": "admin",
            "description": " ",
            "url": "/api/v2/users/1/"
          }
        ]
      },
      "created": "2023-02-01T20:40:48.211226Z",
      "modified": "2023-02-01T20:40:48.211240Z",
      "name": "openstack",
      "description": "",
      "organization": null,
      "credential_type": 6,
      "managed": false,
      "inputs": {
        "host": "https://www.google.com",
        "domain": "",
        "region": "",
        "project": "asdfghj",
        "password": "$encrypted$",
        "username": "adfg",
        "verify_ssl": true,
        "project_domain_name": ""
      },
      "kind": "openstack",
      "cloud": true,
      "kubernetes": false
    },
    {
      "id": 17,
      "type": "credential",
      "url": "/api/v2/credentials/17/",
      "related": {
        "created_by": "/api/v2/users/1/",
        "modified_by": "/api/v2/users/1/",
        "activity_stream": "/api/v2/credentials/17/activity_stream/",
        "access_list": "/api/v2/credentials/17/access_list/",
        "object_roles": "/api/v2/credentials/17/object_roles/",
        "owner_users": "/api/v2/credentials/17/owner_users/",
        "owner_teams": "/api/v2/credentials/17/owner_teams/",
        "copy": "/api/v2/credentials/17/copy/",
        "input_sources": "/api/v2/credentials/17/input_sources/",
        "credential_type": "/api/v2/credential_types/8/",
        "user": "/api/v2/users/1/"
      },
      "summary_fields": {
        "credential_type": {
          "id": 8,
          "name": "Red Hat Satellite 6",
          "description": ""
        },
        "created_by": {
          "id": 1,
          "username": "admin",
          "first_name": "",
          "last_name": ""
        },
        "modified_by": {
          "id": 1,
          "username": "admin",
          "first_name": "",
          "last_name": ""
        },
        "object_roles": {
          "admin_role": {
            "description": "Can manage all aspects of the credential",
            "name": "Admin",
            "id": 460
          },
          "use_role": {
            "description": "Can use the credential in a job template",
            "name": "Use",
            "id": 461
          },
          "read_role": {
            "description": "May view settings for the credential",
            "name": "Read",
            "id": 462
          }
        },
        "user_capabilities": {
          "edit": true,
          "delete": true,
          "copy": true,
          "use": true
        },
        "owners": [
          {
            "id": 1,
            "type": "user",
            "name": "admin",
            "description": " ",
            "url": "/api/v2/users/1/"
          }
        ]
      },
      "created": "2023-02-01T20:41:26.166999Z",
      "modified": "2023-02-01T20:41:26.167012Z",
      "name": "redhat satellite",
      "description": "",
      "organization": null,
      "credential_type": 8,
      "managed": false,
      "inputs": {
        "host": "adfgh",
        "password": "$encrypted$",
        "username": "asdfgh"
      },
      "kind": "satellite6",
      "cloud": true,
      "kubernetes": false
    },
    {
      "id": 18,
      "type": "credential",
      "url": "/api/v2/credentials/18/",
      "related": {
        "created_by": "/api/v2/users/1/",
        "modified_by": "/api/v2/users/1/",
        "activity_stream": "/api/v2/credentials/18/activity_stream/",
        "access_list": "/api/v2/credentials/18/access_list/",
        "object_roles": "/api/v2/credentials/18/object_roles/",
        "owner_users": "/api/v2/credentials/18/owner_users/",
        "owner_teams": "/api/v2/credentials/18/owner_teams/",
        "copy": "/api/v2/credentials/18/copy/",
        "input_sources": "/api/v2/credentials/18/input_sources/",
        "credential_type": "/api/v2/credential_types/14/",
        "user": "/api/v2/users/1/"
      },
      "summary_fields": {
        "credential_type": {
          "id": 14,
          "name": "Red Hat Virtualization",
          "description": ""
        },
        "created_by": {
          "id": 1,
          "username": "admin",
          "first_name": "",
          "last_name": ""
        },
        "modified_by": {
          "id": 1,
          "username": "admin",
          "first_name": "",
          "last_name": ""
        },
        "object_roles": {
          "admin_role": {
            "description": "Can manage all aspects of the credential",
            "name": "Admin",
            "id": 463
          },
          "use_role": {
            "description": "Can use the credential in a job template",
            "name": "Use",
            "id": 464
          },
          "read_role": {
            "description": "May view settings for the credential",
            "name": "Read",
            "id": 465
          }
        },
        "user_capabilities": {
          "edit": true,
          "delete": true,
          "copy": true,
          "use": true
        },
        "owners": [
          {
            "id": 1,
            "type": "user",
            "name": "admin",
            "description": " ",
            "url": "/api/v2/users/1/"
          }
        ]
      },
      "created": "2023-02-01T20:41:52.712221Z",
      "modified": "2023-02-01T20:41:52.712235Z",
      "name": "redhat vm",
      "description": "",
      "organization": null,
      "credential_type": 14,
      "managed": false,
      "inputs": {
        "host": "https://www.google.com",
        "ca_file": "",
        "password": "$encrypted$",
        "username": "asdfgh"
      },
      "kind": "rhv",
      "cloud": true,
      "kubernetes": false
    },
    {
      "id": 16,
      "type": "credential",
      "url": "/api/v2/credentials/16/",
      "related": {
        "created_by": "/api/v2/users/1/",
        "modified_by": "/api/v2/users/1/",
        "activity_stream": "/api/v2/credentials/16/activity_stream/",
        "access_list": "/api/v2/credentials/16/access_list/",
        "object_roles": "/api/v2/credentials/16/object_roles/",
        "owner_users": "/api/v2/credentials/16/owner_users/",
        "owner_teams": "/api/v2/credentials/16/owner_teams/",
        "copy": "/api/v2/credentials/16/copy/",
        "input_sources": "/api/v2/credentials/16/input_sources/",
        "credential_type": "/api/v2/credential_types/15/",
        "user": "/api/v2/users/1/"
      },
      "summary_fields": {
        "credential_type": {
          "id": 15,
          "name": "Red Hat Ansible Automation Platform",
          "description": ""
        },
        "created_by": {
          "id": 1,
          "username": "admin",
          "first_name": "",
          "last_name": ""
        },
        "modified_by": {
          "id": 1,
          "username": "admin",
          "first_name": "",
          "last_name": ""
        },
        "object_roles": {
          "admin_role": {
            "description": "Can manage all aspects of the credential",
            "name": "Admin",
            "id": 457
          },
          "use_role": {
            "description": "Can use the credential in a job template",
            "name": "Use",
            "id": 458
          },
          "read_role": {
            "description": "May view settings for the credential",
            "name": "Read",
            "id": 459
          }
        },
        "user_capabilities": {
          "edit": true,
          "delete": true,
          "copy": true,
          "use": true
        },
        "owners": [
          {
            "id": 1,
            "type": "user",
            "name": "admin",
            "description": " ",
            "url": "/api/v2/users/1/"
          }
        ]
      },
      "created": "2023-02-01T20:41:05.260266Z",
      "modified": "2023-02-01T20:41:05.260280Z",
      "name": "rhaaa",
      "description": "",
      "organization": null,
      "credential_type": 15,
      "managed": false,
      "inputs": {
        "host": "asdfgh",
        "username": "",
        "verify_ssl": false
      },
      "kind": "controller",
      "cloud": true,
      "kubernetes": false
    },
    {
      "id": 11,
      "type": "credential",
      "url": "/api/v2/credentials/11/",
      "related": {
        "created_by": "/api/v2/users/1/",
        "modified_by": "/api/v2/users/1/",
        "activity_stream": "/api/v2/credentials/11/activity_stream/",
        "access_list": "/api/v2/credentials/11/access_list/",
        "object_roles": "/api/v2/credentials/11/object_roles/",
        "owner_users": "/api/v2/credentials/11/owner_users/",
        "owner_teams": "/api/v2/credentials/11/owner_teams/",
        "copy": "/api/v2/credentials/11/copy/",
        "input_sources": "/api/v2/credentials/11/input_sources/",
        "credential_type": "/api/v2/credential_types/3/",
        "user": "/api/v2/users/1/"
      },
      "summary_fields": {
        "credential_type": {
          "id": 3,
          "name": "Vault",
          "description": ""
        },
        "created_by": {
          "id": 1,
          "username": "admin",
          "first_name": "",
          "last_name": ""
        },
        "modified_by": {
          "id": 1,
          "username": "admin",
          "first_name": "",
          "last_name": ""
        },
        "object_roles": {
          "admin_role": {
            "description": "Can manage all aspects of the credential",
            "name": "Admin",
            "id": 316
          },
          "use_role": {
            "description": "Can use the credential in a job template",
            "name": "Use",
            "id": 317
          },
          "read_role": {
            "description": "May view settings for the credential",
            "name": "Read",
            "id": 318
          }
        },
        "user_capabilities": {
          "edit": true,
          "delete": true,
          "copy": true,
          "use": true
        },
        "owners": [
          {
            "id": 1,
            "type": "user",
            "name": "admin",
            "description": " ",
            "url": "/api/v2/users/1/"
          }
        ]
      },
      "created": "2023-01-11T15:39:41.560958Z",
      "modified": "2023-01-11T15:39:41.560972Z",
      "name": "Vault cred",
      "description": "",
      "organization": null,
      "credential_type": 3,
      "managed": false,
      "inputs": {
        "vault_id": "sdfg",
        "vault_password": "$encrypted$"
      },
      "kind": "vault",
      "cloud": false,
      "kubernetes": false
    },
    {
      "id": 19,
      "type": "credential",
      "url": "/api/v2/credentials/19/",
      "related": {
        "created_by": "/api/v2/users/1/",
        "modified_by": "/api/v2/users/1/",
        "activity_stream": "/api/v2/credentials/19/activity_stream/",
        "access_list": "/api/v2/credentials/19/access_list/",
        "object_roles": "/api/v2/credentials/19/object_roles/",
        "owner_users": "/api/v2/credentials/19/owner_users/",
        "owner_teams": "/api/v2/credentials/19/owner_teams/",
        "copy": "/api/v2/credentials/19/copy/",
        "input_sources": "/api/v2/credentials/19/input_sources/",
        "credential_type": "/api/v2/credential_types/7/",
        "user": "/api/v2/users/1/"
      },
      "summary_fields": {
        "credential_type": {
          "id": 7,
          "name": "VMware vCenter",
          "description": ""
        },
        "created_by": {
          "id": 1,
          "username": "admin",
          "first_name": "",
          "last_name": ""
        },
        "modified_by": {
          "id": 1,
          "username": "admin",
          "first_name": "",
          "last_name": ""
        },
        "object_roles": {
          "admin_role": {
            "description": "Can manage all aspects of the credential",
            "name": "Admin",
            "id": 466
          },
          "use_role": {
            "description": "Can use the credential in a job template",
            "name": "Use",
            "id": 467
          },
          "read_role": {
            "description": "May view settings for the credential",
            "name": "Read",
            "id": 468
          }
        },
        "user_capabilities": {
          "edit": true,
          "delete": true,
          "copy": true,
          "use": true
        },
        "owners": [
          {
            "id": 1,
            "type": "user",
            "name": "admin",
            "description": " ",
            "url": "/api/v2/users/1/"
          }
        ]
      },
      "created": "2023-02-01T20:42:13.937422Z",
      "modified": "2023-02-01T20:42:13.937435Z",
      "name": "vmware",
      "description": "",
      "organization": null,
      "credential_type": 7,
      "managed": false,
      "inputs": {
        "host": "https://www.google.com",
        "password": "$encrypted$",
        "username": "asdfgh"
      },
      "kind": "vmware",
      "cloud": true,
      "kubernetes": false
    }
  ]
}
